cluster_task_mag/__init__.py
cluster_task_mag-1.0.1.data/scripts/kill_cluster_job.py
cluster_task_mag-1.0.1.data/scripts/submit_cluster_job.py
cluster_task_mag-1.0.1.dist-info/METADATA
cluster_task_mag-1.0.1.dist-info/WHEEL
cluster_task_mag-1.0.1.dist-info/top_level.txt
cluster_task_mag-1.0.1.dist-info/RECORD
