Metadata-Version: 2.1
Name: cluster-task-mag
Version: 1.0.1
Summary: UNKNOWN
Home-page: UNKNOWN
Author: Min Feng
Author-email: mfeng.geo@gmail.com
License: UNKNOWN
Platform: UNKNOWN
Requires-Dist: geo-raster
